{"programme":{"type":"episode","pid":"p0093y56","expected_child_count":null,"position":null,"image":{"pid":"p01h0rp2"},"media_type":"audio","title":"Lady Soames","short_synopsis":"Sue Lawley\u0027s castaway is the writer Mary Soames","medium_synopsis":"Sue Lawley\u0027s castaway is the writer Mary Soames.","long_synopsis":"The castaway in Desert Island Discs this week is Lady Soames, historian and only surviving child of Winston Churchill. A distinguished author and now Chairman of the Board of the National Theatre, she\u0027ll be talking to Sue Lawley about her extraordinary life - recalling her blissful childhood spent at Chartwell, the family\u0027s country home. She\u0027ll also be talking about the many state visits she made with her father and her husband - and remembering a conversation she had with General de Gaulle, who gave her lots of good advice on the best places to walk dogs in Paris.\n\n[Taken from the original programme material for this archive edition of Desert Island Discs] \n\nFavourite track: Symphony No 6 In F Major Op 68 Pastoral by Ludwig van Beethoven\nBook: Memories From Beyond The Grave by Chateaubriand\nLuxury: Supply of fine Havana cigars","first_broadcast_date":"1992-03-22T12:15:00Z","display_title":{"title":"Desert Island Discs","subtitle":"Lady Soames"},"parent":{"programme":{"type":"brand","pid":"b006qnmr","title":"Desert Island Discs","short_synopsis":"Kirsty Young invites her castaway guests to share the soundtrack of their lives.","position":null,"image":{"pid":"p05g24sc"},"expected_child_count":null,"first_broadcast_date":"1942-01-29T19:00:00+01:00","aggregated_episode_count":3147,"ownership":{"service":{"type":"radio","id":"bbc_radio_four","key":"radio4","title":"BBC Radio 4"}}}},"peers":{"previous":{"type":"episode","pid":"p0093y6n","title":"Sir Isaiah Berlin","first_broadcast_date":"1992-03-15T12:15:00Z","position":null,"media_type":"audio"},"next":{"type":"episode","pid":"p0093y4d","title":"Sir Ernst Gombrich","first_broadcast_date":"1992-04-05T12:15:00+01:00","position":null,"media_type":"audio"}},"versions":[{"canonical":1,"pid":"p0093y59","duration":2400,"types":["Original version"]},{"canonical":0,"pid":"p02ppfdc","duration":2355,"types":["Podcast version"]}],"links":[],"supporting_content_items":[],"categories":[{"type":"format","id":"PT004","key":"discussionandtalk","title":"Discussion \u0026 Talk","narrower":[],"broader":{},"has_topic_page":false,"sameAs":null},{"type":"genre","id":"C00050","key":"lifestories","title":"Life Stories","narrower":[],"broader":{"category":{"type":"genre","id":"C00045","key":"factual","title":"Factual","broader":{},"has_topic_page":false,"sameAs":null}},"has_topic_page":false,"sameAs":null}]}}