{"programme":{"type":"episode","pid":"p00947t6","expected_child_count":null,"position":null,"image":{"pid":"p01gzyh6"},"media_type":"audio","title":"Betty Jackson","short_synopsis":"Sue Lawley\u0027s castaway is designer Betty Jackson","medium_synopsis":"Sue Lawley\u0027s castaway is designer Betty Jackson.","long_synopsis":"This week the castaway on Desert Island Discs is the fashion designer Betty Jackson. For three decades Betty Jackson has been at the cutting edge of the British Fashion scene and this year presented her 40th show at London Fashion week. In conversation with Sue Lawley, she talks about her life and work and chooses eight records to take to the mythical island.\n\n[Taken from the original programme material for this archive edition of Desert Island Discs]\n\nFavourite track: You Don\u0027t Have To Say You Love Me by Dusty Springfield\nBook: Vision: 50 Years of Creativity by Melvyn Bragg\nLuxury: Red lipstick","first_broadcast_date":"2002-04-28T11:15:00+01:00","display_title":{"title":"Desert Island Discs","subtitle":"Betty Jackson"},"parent":{"programme":{"type":"brand","pid":"b006qnmr","title":"Desert Island Discs","short_synopsis":"Kirsty Young invites her castaway guests to share the soundtrack of their lives.","position":null,"image":{"pid":"p05g24sc"},"expected_child_count":null,"first_broadcast_date":"1942-01-29T19:00:00+01:00","aggregated_episode_count":3147,"ownership":{"service":{"type":"radio","id":"bbc_radio_four","key":"radio4","title":"BBC Radio 4"}}}},"peers":{"previous":{"type":"episode","pid":"p00947v0","title":"Wayne Marshall","first_broadcast_date":"2002-04-21T11:15:00+01:00","position":null,"media_type":"audio"},"next":{"type":"episode","pid":"p00947s3","title":"Jude Kelly","first_broadcast_date":"2002-05-05T11:15:00+01:00","position":null,"media_type":"audio"}},"versions":[{"canonical":1,"pid":"p00947t9","duration":2700,"types":["Original version"]},{"canonical":0,"pid":"p02pnzcp","duration":1982,"types":["Podcast version"]}],"links":[],"supporting_content_items":[],"categories":[{"type":"format","id":"PT004","key":"discussionandtalk","title":"Discussion \u0026 Talk","narrower":[],"broader":{},"has_topic_page":false,"sameAs":null},{"type":"genre","id":"C00050","key":"lifestories","title":"Life Stories","narrower":[],"broader":{"category":{"type":"genre","id":"C00045","key":"factual","title":"Factual","broader":{},"has_topic_page":false,"sameAs":null}},"has_topic_page":false,"sameAs":null}]}}