{"programme":{"type":"episode","pid":"p0094375","expected_child_count":null,"position":null,"image":{"pid":"p01h7wjs"},"media_type":"audio","title":"Geoffrey Smith","short_synopsis":"Sue Lawley\u0027s castaway is gardener and broadcaster Geoffrey Smith","medium_synopsis":"Sue Lawley\u0027s castaway is gardener and broadcaster Geoffrey Smith.","long_synopsis":"Sue Lawley\u0027s castaway this week is the gardener and broadcaster Geoffrey Smith. He learnt his craft at his father\u0027s knee growing fruit and vegetables for the stately home where he worked. Later he learnt the science of horticulture at college and achieved top marks. He\u0027s always maintained the promise he made to himself as a boy: to spend his life outdoors. Except, of course, when he enters a studio for Radio 4\u0027s Gardeners\u0027 Question Time.\n\n[Taken from the original programme material for this archive edition of Desert Island Discs] \n\nFavourite track: Dawn Chorus\nBook: History of viticulture, with instructions on how to make wine\nLuxury: Bundle of prunings from a good vineyard so he can plant his own vines","first_broadcast_date":"1998-06-07T11:15:00+01:00","display_title":{"title":"Desert Island Discs","subtitle":"Geoffrey Smith"},"parent":{"programme":{"type":"brand","pid":"b006qnmr","title":"Desert Island Discs","short_synopsis":"Kirsty Young invites her castaway guests to share the soundtrack of their lives.","position":null,"image":{"pid":"p05g24sc"},"expected_child_count":null,"first_broadcast_date":"1942-01-29T19:00:00+01:00","aggregated_episode_count":3147,"ownership":{"service":{"type":"radio","id":"bbc_radio_four","key":"radio4","title":"BBC Radio 4"}}}},"peers":{"previous":{"type":"episode","pid":"p009437w","title":"John Harle","first_broadcast_date":"1998-05-24T11:15:00+01:00","position":null,"media_type":"audio"},"next":{"type":"episode","pid":"p009436f","title":"Bill Kenwright","first_broadcast_date":"1998-06-14T11:15:00+01:00","position":null,"media_type":"audio"}},"versions":[{"canonical":1,"pid":"p0094378","duration":2700,"types":["Original version"]},{"canonical":0,"pid":"p02ppfv5","duration":2207,"types":["Podcast version"]}],"links":[],"supporting_content_items":[],"categories":[{"type":"format","id":"PT004","key":"discussionandtalk","title":"Discussion \u0026 Talk","narrower":[],"broader":{},"has_topic_page":false,"sameAs":null},{"type":"genre","id":"C00050","key":"lifestories","title":"Life Stories","narrower":[],"broader":{"category":{"type":"genre","id":"C00045","key":"factual","title":"Factual","broader":{},"has_topic_page":false,"sameAs":null}},"has_topic_page":false,"sameAs":null}]}}